caped_ai/__init__.py
caped_ai/_version.py
caped_ai/oneat.py
caped_ai/vollseg.py
caped_ai-1.0.4.dist-info/METADATA
caped_ai-1.0.4.dist-info/WHEEL
caped_ai-1.0.4.dist-info/top_level.txt
caped_ai-1.0.4.dist-info/RECORD
