Metadata-Version: 2.1
Name: caped-ai
Version: 1.0.4
Summary: Content aware prediction and detection based on artificial intelligence.
Home-page: https://github.com/Kapoorlabs-CAPED/CAPED-AI/
Author: Varun Kapoor
Author-email: varun.kapoor@kapoorlabs.org
Classifier: Development Status :: 3 - Alpha
Classifier: Natural Language :: English
Classifier: License :: OSI Approved :: MIT License
Classifier: Operating System :: OS Independent
Classifier: Programming Language :: Python
Classifier: Programming Language :: Python :: 3.9
Requires-Dist: oneat
Requires-Dist: hydra-core
Requires-Dist: caped-ai-metrics
Requires-Dist: caped-ai-mtrack
Requires-Dist: caped-ai-tabulour
Requires-Dist: caped-ai-augmentations
Requires-Dist: napatrackmater
Requires-Dist: rdp
